{
  "url": "https://mp.weixin.qq.com/cgi-bin/appmsgpublish?sub=list&begin=0&count=10&token=941781265&lang=zh_CN&_=1779430178221",
  "pops": [
    {
      "i": 0,
      "tag": "DIV",
      "cls": "weui-desktop-popover__wrp popover-adjust",
      "text": "发表相关数据均为实时人数",
      "box": {
        "x": 408.0888366699219,
        "y": 42.40702438354492,
        "w": 20,
        "h": 22.747934341430664
      },
      "buttons": []
    },
    {
      "i": 1,
      "tag": "DIV",
      "cls": "weui-desktop-popover__wrp weui-desktop-mass__status_pop",
      "text": "已发表",
      "box": {
        "x": 338.09918212890625,
        "y": 224.5557861328125,
        "w": 63.977272033691406,
        "h": 17.851240158081055
      },
      "buttons": []
    },
    {
      "i": 2,
      "tag": "DIV",
      "cls": "weui-desktop-popover__wrp",
      "text": "置顶 仅自己可见 删除 关闭推荐 复制链接 \n                  添加合集\n                  声明创作来源",
      "box": {
        "x": 1538.1715087890625,
        "y": 205.57850646972656,
        "w": 35.99173355102539,
        "h": 35.99173355102539
      },
      "buttons": []
    },
    {
      "i": 3,
      "tag": "DIV",
      "cls": "weui-desktop-popover__wrp weui-desktop-mass__status_pop",
      "text": "已发表",
      "box": {
        "x": 338.09918212890625,
        "y": 368.522705078125,
        "w": 63.977272033691406,
        "h": 17.851240158081055
      },
      "buttons": []
    },
    {
      "i": 4,
      "tag": "DIV",
      "cls": "weui-desktop-popover__wrp",
      "text": "置顶 仅自己可见 删除 关闭推荐 复制链接 \n                  添加合集\n                  声明创作来源",
      "box": {
        "x": 1538.1715087890625,
        "y": 349.5454406738281,
        "w": 35.99173355102539,
        "h": 35.99173355102539
      },
      "buttons": []
    },
    {
      "i": 5,
      "tag": "DIV",
      "cls": "weui-desktop-popover__wrp weui-desktop-mass__status_pop",
      "text": "已发表",
      "box": {
        "x": 338.09918212890625,
        "y": 512.4896850585938,
        "w": 63.977272033691406,
        "h": 17.851240158081055
      },
      "buttons": []
    },
    {
      "i": 6,
      "tag": "DIV",
      "cls": "weui-desktop-popover__wrp",
      "text": "置顶 仅自己可见 删除 关闭推荐 复制链接 \n                  添加合集\n                  声明创作来源",
      "box": {
        "x": 1538.1715087890625,
        "y": 493.51239013671875,
        "w": 35.99173355102539,
        "h": 35.99173355102539
      },
      "buttons": []
    },
    {
      "i": 7,
      "tag": "DIV",
      "cls": "weui-desktop-popover__wrp weui-desktop-mass__status_pop",
      "text": "已发表",
      "box": {
        "x": 338.09918212890625,
        "y": 656.4566040039062,
        "w": 63.977272033691406,
        "h": 17.851240158081055
      },
      "buttons": []
    },
    {
      "i": 8,
      "tag": "DIV",
      "cls": "weui-desktop-popover__wrp",
      "text": "置顶 仅自己可见 删除 关闭推荐 复制链接 \n                  添加合集\n                  声明创作来源",
      "box": {
        "x": 1538.1715087890625,
        "y": 637.4793090820312,
        "w": 35.99173355102539,
        "h": 35.99173355102539
      },
      "buttons": []
    },
    {
      "i": 9,
      "tag": "DIV",
      "cls": "weui-desktop-popover__wrp weui-desktop-mass__status_pop",
      "text": "已发表",
      "box": {
        "x": 338.09918212890625,
        "y": 800.4235229492188,
        "w": 63.977272033691406,
        "h": 17.851240158081055
      },
      "buttons": []
    },
    {
      "i": 10,
      "tag": "DIV",
      "cls": "weui-desktop-popover__wrp",
      "text": "置顶 仅自己可见 删除 关闭推荐 复制链接 \n                  添加合集\n                  声明创作来源",
      "box": {
        "x": 1538.1715087890625,
        "y": 781.4462890625,
        "w": 35.99173355102539,
        "h": 35.99173355102539
      },
      "buttons": []
    },
    {
      "i": 11,
      "tag": "DIV",
      "cls": "weui-desktop-popover__wrp weui-desktop-mass__status_pop",
      "text": "已发表",
      "box": {
        "x": 338.09918212890625,
        "y": 944.3905029296875,
        "w": 63.977272033691406,
        "h": 17.851240158081055
      },
      "buttons": []
    },
    {
      "i": 12,
      "tag": "DIV",
      "cls": "weui-desktop-popover__wrp",
      "text": "置顶 仅自己可见 删除 关闭推荐 复制链接 \n                  添加合集\n                  声明创作来源",
      "box": {
        "x": 1538.1715087890625,
        "y": 925.4132080078125,
        "w": 35.99173355102539,
        "h": 35.99173355102539
      },
      "buttons": []
    },
    {
      "i": 13,
      "tag": "DIV",
      "cls": "weui-desktop-popover__wrp weui-desktop-mass__status_pop",
      "text": "已发表",
      "box": {
        "x": 338.09918212890625,
        "y": 1088.357421875,
        "w": 63.977272033691406,
        "h": 17.851240158081055
      },
      "buttons": []
    },
    {
      "i": 14,
      "tag": "DIV",
      "cls": "weui-desktop-popover__wrp",
      "text": "置顶 仅自己可见 删除 关闭推荐 复制链接 \n                  添加合集\n                  声明创作来源",
      "box": {
        "x": 1538.1715087890625,
        "y": 1069.380126953125,
        "w": 35.99173355102539,
        "h": 35.99173355102539
      },
      "buttons": []
    },
    {
      "i": 15,
      "tag": "DIV",
      "cls": "weui-desktop-popover__wrp weui-desktop-mass__status_pop",
      "text": "已发表",
      "box": {
        "x": 338.09918212890625,
        "y": 1232.3243408203125,
        "w": 63.977272033691406,
        "h": 17.851240158081055
      },
      "buttons": []
    },
    {
      "i": 16,
      "tag": "DIV",
      "cls": "weui-desktop-popover__wrp",
      "text": "置顶 仅自己可见 删除 关闭推荐 复制链接 \n                  添加合集\n                  声明创作来源",
      "box": {
        "x": 1538.1715087890625,
        "y": 1213.3470458984375,
        "w": 35.99173355102539,
        "h": 35.99173355102539
      },
      "buttons": []
    },
    {
      "i": 17,
      "tag": "DIV",
      "cls": "weui-desktop-popover__wrp weui-desktop-mass__status_pop",
      "text": "已发表",
      "box": {
        "x": 338.09918212890625,
        "y": 1376.291259765625,
        "w": 63.977272033691406,
        "h": 17.851240158081055
      },
      "buttons": []
    },
    {
      "i": 18,
      "tag": "DIV",
      "cls": "weui-desktop-popover__wrp",
      "text": "置顶 仅自己可见 删除 关闭推荐 复制链接 \n                  添加合集\n                  声明创作来源",
      "box": {
        "x": 1538.1715087890625,
        "y": 1357.31396484375,
        "w": 35.99173355102539,
        "h": 35.99173355102539
      },
      "buttons": []
    },
    {
      "i": 19,
      "tag": "DIV",
      "cls": "weui-desktop-popover__wrp weui-desktop-mass__status_pop",
      "text": "已发表",
      "box": {
        "x": 338.09918212890625,
        "y": 1520.2581787109375,
        "w": 63.977272033691406,
        "h": 17.851240158081055
      },
      "buttons": []
    },
    {
      "i": 20,
      "tag": "DIV",
      "cls": "weui-desktop-popover__wrp",
      "text": "置顶 仅自己可见 删除 关闭推荐 复制链接 \n                  添加合集\n                  声明创作来源",
      "box": {
        "x": 1538.1715087890625,
        "y": 1501.281005859375,
        "w": 35.99173355102539,
        "h": 35.99173355102539
      },
      "buttons": []
    }
  ],
  "all": [
    {
      "i": 0,
      "text": "首页\n内容管理\n草稿箱\n素材库\n发表记录\n原创\n合集\n互动管理\n留言\n划线\n私信\n提到\n投票\n视频弹幕\n自动回复\n自定义菜单\n用户管理\n号内搜索\n数据分析\n收入变现\n赞赏\n付费\n带货\n流量主\n微信小店\n广告与服务\n广告主\n小程序管理\n模板消息\n微信搜一搜\n微信支付\n服务市场\n设置与开发\n新的功能\n通知中心\n45\nsinnple coffee\n发表记录\n全部 12\n已通知 6\n未通知 6\n置顶 0\n今天 14:01\n已发表\n我本地跑了一遍 HTML-in-Canvas：能跑，但还远不是生产级\n1\n0\n0\n0\n0\n0\n  \n还可以修改3次\n \n今天 12:35\n已发表\n四个 HTML Skill 横向对比：谁负责审美，谁负责文章，谁负责交付\n2\n0\n0\n0\n0\n0\n今天 12:33\n已发表\n我把 Codex 接到飞书后，最大的变化不是“手机能聊天”\n1\n0\n0\n0\n0\n0\n今天 12:25\n已发表\n真实浏览器爬取方案重新评定\n1\n0\n0\n0\n0\n0\n今天 10:19\n已发表\n【测试勿发】四个 HTML Skill 横向对比\n2\n0\n0\n0\n0\n0\n今天 03:50\n已发表\n比特、MoreLogin、AdsPower 三款指纹浏览器实测对比\n11\n0\n1\n0\n0\n0\n昨天 11:39\n已发表\n我把 Codex 接到飞书后，最大的变化不是“手机能聊天”\n10\n0\n0\n0\n0\n0\n昨天 11:35\n已发表\n四个 HTML Skill 横向对比：谁负责审美，谁负责文章，谁负责交付\n10\n0\n0\n0\n0\n0\n昨天 11:25\n已发表\n真实浏览器爬取方案重新评定\n3\n0\n0\n0\n0\n0\n05月07日\n已发表\n1块钱用上 Opus 4.6/4.7？Windsurf 低价体验路线\n133\n0\n3\n0\n0\n0\n1 2 下一页  跳转",
      "cls": "mp-body",
      "href": "",
      "box": {
        "x": 0,
        "y": 0,
        "w": 1687.272705078125,
        "h": 1707.004150390625
      }
    },
    {
      "i": 1,
      "text": "首页\n内容管理\n草稿箱\n素材库\n发表记录\n原创\n合集\n互动管理\n留言\n划线\n私信\n提到\n投票\n视频弹幕\n自动回复\n自定义菜单\n用户管理\n号内搜索\n数据分析\n收入变现\n赞赏\n付费\n带货\n流量主\n微信小店\n广告与服务\n广告主\n小程序管理\n模板消息\n微信搜一搜\n微信支付\n服务市场\n设置与开发\n新的功能\n通知中心\n45\nsinnple coffee\n发表记录\n全部 12\n已通知 6\n未通知 6\n置顶 0\n今天 14:01\n已发表\n我本地跑了一遍 HTML-in-Canvas：能跑，但还远不是生产级\n1\n0\n0\n0\n0\n0\n  \n还可以修改3次\n \n今天 12:35\n已发表\n四个 HTML Skill 横向对比：谁负责审美，谁负责文章，谁负责交付\n2\n0\n0\n0\n0\n0\n今天 12:33\n已发表\n我把 Codex 接到飞书后，最大的变化不是“手机能聊天”\n1\n0\n0\n0\n0\n0\n今天 12:25\n已发表\n真实浏览器爬取方案重新评定\n1\n0\n0\n0\n0\n0\n今天 10:19\n已发表\n【测试勿发】四个 HTML Skill 横向对比\n2\n0\n0\n0\n0\n0\n今天 03:50\n已发表\n比特、MoreLogin、AdsPower 三款指纹浏览器实测对比\n11\n0\n1\n0\n0\n0\n昨天 11:39\n已发表\n我把 Codex 接到飞书后，最大的变化不是“手机能聊天”\n10\n0\n0\n0\n0\n0\n昨天 11:35\n已发表\n四个 HTML Skill 横向对比：谁负责审美，谁负责文章，谁负责交付\n10\n0\n0\n0\n0\n0\n昨天 11:25\n已发表\n真实浏览器爬取方案重新评定\n3\n0\n0\n0\n0\n0\n05月07日\n已发表\n1块钱用上 Opus 4.6/4.7？Windsurf 低价体验路线\n133\n0\n3\n0\n0\n0\n1 2 下一页  跳转",
      "cls": "weui-desktop-layout weui-desktop-layout_global",
      "href": "",
      "box": {
        "x": 0,
        "y": 31.99380111694336,
        "w": 1687.272705078125,
        "h": 1611.0123291015625
      }
    },
    {
      "i": 4,
      "text": "首页\n内容管理\n草稿箱\n素材库\n发表记录\n原创\n合集\n互动管理\n留言\n划线\n私信\n提到\n投票\n视频弹幕\n自动回复\n自定义菜单\n用户管理\n号内搜索\n数据分析\n收入变现\n赞赏\n付费\n带货\n流量主\n微信小店\n广告与服务\n广告主\n小程序管理\n模板消息\n微信搜一搜\n微信支付\n服务市场\n设置与开发\n新的功能\n通知中心\n45\nsinnple coffee",
      "cls": "weui-desktop-layout__side weui-desktop-layout__side-menu",
      "href": "",
      "box": {
        "x": 0,
        "y": 0,
        "w": 231.99378967285156,
        "h": 866.1156616210938
      }
    },
    {
      "i": 5,
      "text": "首页\n内容管理\n草稿箱\n素材库\n发表记录\n原创\n合集\n互动管理\n留言\n划线\n私信\n提到\n投票\n视频弹幕\n自动回复\n自定义菜单\n用户管理\n号内搜索\n数据分析\n收入变现\n赞赏\n付费\n带货\n流量主\n微信小店\n广告与服务\n广告主\n小程序管理\n模板消息\n微信搜一搜\n微信支付\n服务市场\n设置与开发\n新的功能\n通知中心\n45\nsinnple coffee",
      "cls": "js_global_menu weui-desktop-layout__side-menu__container weui-desktop-layout__side-menu__overflown",
      "href": "",
      "box": {
        "x": 0,
        "y": 31.99380111694336,
        "w": 231.99378967285156,
        "h": 834.1218872070312
      }
    },
    {
      "i": 8,
      "text": "首页\n内容管理\n草稿箱\n素材库\n发表记录\n原创\n合集\n互动管理\n留言\n划线\n私信\n提到\n投票\n视频弹幕\n自动回复\n自定义菜单\n用户管理\n号内搜索\n数据分析\n收入变现\n赞赏\n付费\n带货\n流量主\n微信小店\n广告与服务\n广告主\n小程序管理\n模板消息\n微信搜一搜\n微信支付\n服务市场\n设置与开发\n新的功能",
      "cls": "weui-desktop-menu_global-wrapper",
      "href": "",
      "box": {
        "x": 0,
        "y": 83.98760223388672,
        "w": 231.99378967285156,
        "h": 642.16943359375
      }
    },
    {
      "i": 12,
      "text": "内容管理",
      "cls": "weui-desktop-menu__link",
      "href": "",
      "box": {
        "x": 15.991735458374023,
        "y": 143.96693420410156,
        "w": 200.0103302001953,
        "h": 53.98760223388672
      }
    },
    {
      "i": 13,
      "text": "内容管理",
      "cls": "weui-desktop-menu__link__inner",
      "href": "",
      "box": {
        "x": 31.983470916748047,
        "y": 159.95867919921875,
        "w": 94.00826263427734,
        "h": 22.004131317138672
      }
    },
    {
      "i": 14,
      "text": "内容管理",
      "cls": "weui-desktop-menu__name",
      "href": "",
      "box": {
        "x": 31.983470916748047,
        "y": 159.95867919921875,
        "w": 94.00826263427734,
        "h": 22.004131317138672
      }
    },
    {
      "i": 130,
      "text": "发表记录\n全部 12\n已通知 6\n未通知 6\n置顶 0\n今天 14:01\n已发表\n我本地跑了一遍 HTML-in-Canvas：能跑，但还远不是生产级\n1\n0\n0\n0\n0\n0\n  \n还可以修改3次\n \n今天 12:35\n已发表\n四个 HTML Skill 横向对比：谁负责审美，谁负责文章，谁负责交付\n2\n0\n0\n0\n0\n0\n今天 12:33\n已发表\n我把 Codex 接到飞书后，最大的变化不是“手机能聊天”\n1\n0\n0\n0\n0\n0\n今天 12:25\n已发表\n真实浏览器爬取方案重新评定\n1\n0\n0\n0\n0\n0\n今天 10:19\n已发表\n【测试勿发】四个 HTML Skill 横向对比\n2\n0\n0\n0\n0\n0\n今天 03:50\n已发表\n比特、MoreLogin、AdsPower 三款指纹浏览器实测对比\n11\n0\n1\n0\n0\n0\n昨天 11:39\n已发表\n我把 Codex 接到飞书后，最大的变化不是“手机能聊天”\n10\n0\n0\n0\n0\n0\n昨天 11:35\n已发表\n四个 HTML Skill 横向对比：谁负责审美，谁负责文章，谁负责交付\n10\n0\n0\n0\n0\n0\n昨天 11:25\n已发表\n真实浏览器爬取方案重新评定\n3\n0\n0\n0\n0\n0\n05月07日\n已发表\n1块钱用上 Opus 4.6/4.7？Windsurf 低价体验路线\n133\n0\n3\n0\n0\n0\n1 2 下一页  跳转",
      "cls": "weui-desktop-layout__main",
      "href": "",
      "box": {
        "x": 225,
        "y": 32.98553466796875,
        "w": 1462.272705078125,
        "h": 1610.0206298828125
      }
    },
    {
      "i": 131,
      "text": "发表记录\n全部 12\n已通知 6\n未通知 6\n置顶 0\n今天 14:01\n已发表\n我本地跑了一遍 HTML-in-Canvas：能跑，但还远不是生产级\n1\n0\n0\n0\n0\n0\n  \n还可以修改3次\n \n今天 12:35\n已发表\n四个 HTML Skill 横向对比：谁负责审美，谁负责文章，谁负责交付\n2\n0\n0\n0\n0\n0\n今天 12:33\n已发表\n我把 Codex 接到飞书后，最大的变化不是“手机能聊天”\n1\n0\n0\n0\n0\n0\n今天 12:25\n已发表\n真实浏览器爬取方案重新评定\n1\n0\n0\n0\n0\n0\n今天 10:19\n已发表\n【测试勿发】四个 HTML Skill 横向对比\n2\n0\n0\n0\n0\n0\n今天 03:50\n已发表\n比特、MoreLogin、AdsPower 三款指纹浏览器实测对比\n11\n0\n1\n0\n0\n0\n昨天 11:39\n已发表\n我把 Codex 接到飞书后，最大的变化不是“手机能聊天”\n10\n0\n0\n0\n0\n0\n昨天 11:35\n已发表\n四个 HTML Skill 横向对比：谁负责审美，谁负责文章，谁负责交付\n10\n0\n0\n0\n0\n0\n昨天 11:25\n已发表\n真实浏览器爬取方案重新评定\n3\n0\n0\n0\n0\n0\n05月07日\n已发表\n1块钱用上 Opus 4.6/4.7？Windsurf 低价体验路线\n133\n0\n3\n0\n0\n0\n1 2 下一页  跳转",
      "cls": "weui-desktop-layout__main__area",
      "href": "",
      "box": {
        "x": 225,
        "y": 32.98553466796875,
        "w": 1462.272705078125,
        "h": 1610.0206298828125
      }
    },
    {
      "i": 132,
      "text": "发表记录\n全部 12\n已通知 6\n未通知 6\n置顶 0\n今天 14:01\n已发表\n我本地跑了一遍 HTML-in-Canvas：能跑，但还远不是生产级\n1\n0\n0\n0\n0\n0\n  \n还可以修改3次\n \n今天 12:35\n已发表\n四个 HTML Skill 横向对比：谁负责审美，谁负责文章，谁负责交付\n2\n0\n0\n0\n0\n0\n今天 12:33\n已发表\n我把 Codex 接到飞书后，最大的变化不是“手机能聊天”\n1\n0\n0\n0\n0\n0\n今天 12:25\n已发表\n真实浏览器爬取方案重新评定\n1\n0\n0\n0\n0\n0\n今天 10:19\n已发表\n【测试勿发】四个 HTML Skill 横向对比\n2\n0\n0\n0\n0\n0\n今天 03:50\n已发表\n比特、MoreLogin、AdsPower 三款指纹浏览器实测对比\n11\n0\n1\n0\n0\n0\n昨天 11:39\n已发表\n我把 Codex 接到飞书后，最大的变化不是“手机能聊天”\n10\n0\n0\n0\n0\n0\n昨天 11:35\n已发表\n四个 HTML Skill 横向对比：谁负责审美，谁负责文章，谁负责交付\n10\n0\n0\n0\n0\n0\n昨天 11:25\n已发表\n真实浏览器爬取方案重新评定\n3\n0\n0\n0\n0\n0\n05月07日\n已发表\n1块钱用上 Opus 4.6/4.7？Windsurf 低价体验路线\n133\n0\n3\n0\n0\n0\n1 2 下一页  跳转",
      "cls": "weui-desktop-layout__main__inner",
      "href": "",
      "box": {
        "x": 298.1094970703125,
        "y": 32.98553466796875,
        "w": 1316.0433349609375,
        "h": 1610.0206298828125
      }
    },
    {
      "i": 133,
      "text": "发表记录\n全部 12\n已通知 6\n未通知 6\n置顶 0\n今天 14:01\n已发表\n我本地跑了一遍 HTML-in-Canvas：能跑，但还远不是生产级\n1\n0\n0\n0\n0\n0\n  \n还可以修改3次\n \n今天 12:35\n已发表\n四个 HTML Skill 横向对比：谁负责审美，谁负责文章，谁负责交付\n2\n0\n0\n0\n0\n0\n今天 12:33\n已发表\n我把 Codex 接到飞书后，最大的变化不是“手机能聊天”\n1\n0\n0\n0\n0\n0\n今天 12:25\n已发表\n真实浏览器爬取方案重新评定\n1\n0\n0\n0\n0\n0\n今天 10:19\n已发表\n【测试勿发】四个 HTML Skill 横向对比\n2\n0\n0\n0\n0\n0\n今天 03:50\n已发表\n比特、MoreLogin、AdsPower 三款指纹浏览器实测对比\n11\n0\n1\n0\n0\n0\n昨天 11:39\n已发表\n我把 Codex 接到飞书后，最大的变化不是“手机能聊天”\n10\n0\n0\n0\n0\n0\n昨天 11:35\n已发表\n四个 HTML Skill 横向对比：谁负责审美，谁负责文章，谁负责交付\n10\n0\n0\n0\n0\n0\n昨天 11:25\n已发表\n真实浏览器爬取方案重新评定\n3\n0\n0\n0\n0\n0\n05月07日\n已发表\n1块钱用上 Opus 4.6/4.7？Windsurf 低价体验路线\n133\n0\n3\n0\n0\n0\n1 2 下一页  跳转",
      "cls": "",
      "href": "",
      "box": {
        "x": 298.1094970703125,
        "y": 32.98553466796875,
        "w": 1316.0433349609375,
        "h": 1610.0206298828125
      }
    },
    {
      "i": 134,
      "text": "发表记录\n全部 12\n已通知 6\n未通知 6\n置顶 0\n今天 14:01\n已发表\n我本地跑了一遍 HTML-in-Canvas：能跑，但还远不是生产级\n1\n0\n0\n0\n0\n0\n  \n还可以修改3次\n \n今天 12:35\n已发表\n四个 HTML Skill 横向对比：谁负责审美，谁负责文章，谁负责交付\n2\n0\n0\n0\n0\n0\n今天 12:33\n已发表\n我把 Codex 接到飞书后，最大的变化不是“手机能聊天”\n1\n0\n0\n0\n0\n0\n今天 12:25\n已发表\n真实浏览器爬取方案重新评定\n1\n0\n0\n0\n0\n0\n今天 10:19\n已发表\n【测试勿发】四个 HTML Skill 横向对比\n2\n0\n0\n0\n0\n0\n今天 03:50\n已发表\n比特、MoreLogin、AdsPower 三款指纹浏览器实测对比\n11\n0\n1\n0\n0\n0\n昨天 11:39\n已发表\n我把 Codex 接到飞书后，最大的变化不是“手机能聊天”\n10\n0\n0\n0\n0\n0\n昨天 11:35\n已发表\n四个 HTML Skill 横向对比：谁负责审美，谁负责文章，谁负责交付\n10\n0\n0\n0\n0\n0\n昨天 11:25\n已发表\n真实浏览器爬取方案重新评定\n3\n0\n0\n0\n0\n0\n05月07日\n已发表\n1块钱用上 Opus 4.6/4.7？Windsurf 低价体验路线\n133\n0\n3\n0\n0\n0\n1 2 下一页  跳转",
      "cls": "",
      "href": "",
      "box": {
        "x": 298.1094970703125,
        "y": 32.98553466796875,
        "w": 1316.0433349609375,
        "h": 1610.0206298828125
      }
    },
    {
      "i": 135,
      "text": "发表记录\n全部 12\n已通知 6\n未通知 6\n置顶 0\n今天 14:01\n已发表\n我本地跑了一遍 HTML-in-Canvas：能跑，但还远不是生产级\n1\n0\n0\n0\n0\n0\n  \n还可以修改3次\n \n今天 12:35\n已发表\n四个 HTML Skill 横向对比：谁负责审美，谁负责文章，谁负责交付\n2\n0\n0\n0\n0\n0\n今天 12:33\n已发表\n我把 Codex 接到飞书后，最大的变化不是“手机能聊天”\n1\n0\n0\n0\n0\n0\n今天 12:25\n已发表\n真实浏览器爬取方案重新评定\n1\n0\n0\n0\n0\n0\n今天 10:19\n已发表\n【测试勿发】四个 HTML Skill 横向对比\n2\n0\n0\n0\n0\n0\n今天 03:50\n已发表\n比特、MoreLogin、AdsPower 三款指纹浏览器实测对比\n11\n0\n1\n0\n0\n0\n昨天 11:39\n已发表\n我把 Codex 接到飞书后，最大的变化不是“手机能聊天”\n10\n0\n0\n0\n0\n0\n昨天 11:35\n已发表\n四个 HTML Skill 横向对比：谁负责审美，谁负责文章，谁负责交付\n10\n0\n0\n0\n0\n0\n昨天 11:25\n已发表\n真实浏览器爬取方案重新评定\n3\n0\n0\n0\n0\n0\n05月07日\n已发表\n1块钱用上 Opus 4.6/4.7？Windsurf 低价体验路线\n133\n0\n3\n0\n0\n0\n1 2 下一页  跳转",
      "cls": "publish_history_page",
      "href": "",
      "box": {
        "x": 298.1094970703125,
        "y": 32.98553466796875,
        "w": 1316.0433349609375,
        "h": 1610.0206298828125
      }
    },
    {
      "i": 158,
      "text": "今天 14:01\n已发表\n我本地跑了一遍 HTML-in-Canvas：能跑，但还远不是生产级\n1\n0\n0\n0\n0\n0\n  \n还可以修改3次\n \n今天 12:35\n已发表\n四个 HTML Skill 横向对比：谁负责审美，谁负责文章，谁负责交付\n2\n0\n0\n0\n0\n0\n今天 12:33\n已发表\n我把 Codex 接到飞书后，最大的变化不是“手机能聊天”\n1\n0\n0\n0\n0\n0\n今天 12:25\n已发表\n真实浏览器爬取方案重新评定\n1\n0\n0\n0\n0\n0\n今天 10:19\n已发表\n【测试勿发】四个 HTML Skill 横向对比\n2\n0\n0\n0\n0\n0\n今天 03:50\n已发表\n比特、MoreLogin、AdsPower 三款指纹浏览器实测对比\n11\n0\n1\n0\n0\n0\n昨天 11:39\n已发表\n我把 Codex 接到飞书后，最大的变化不是“手机能聊天”\n10\n0\n0\n0\n0\n0\n昨天 11:35\n已发表\n四个 HTML Skill 横向对比：谁负责审美，谁负责文章，谁负责交付\n10\n0\n0\n0\n0\n0\n昨天 11:25\n已发表\n真实浏览器爬取方案重新评定\n3\n0\n0\n0\n0\n0\n05月07日\n已发表\n1块钱用上 Opus 4.6/4.7？Windsurf 低价体验路线\n133\n0\n3\n0\n0\n0\n1 2 下一页  跳转",
      "cls": "publish_content publish_record_history",
      "href": "",
      "box": {
        "x": 298.1094970703125,
        "y": 158.58470153808594,
        "w": 1316.0433349609375,
        "h": 1484.4215087890625
      }
    },
    {
      "i": 159,
      "text": "今天 14:01\n已发表\n我本地跑了一遍 HTML-in-Canvas：能跑，但还远不是生产级\n1\n0\n0\n0\n0\n0\n  \n还可以修改3次\n \n今天 12:35\n已发表\n四个 HTML Skill 横向对比：谁负责审美，谁负责文章，谁负责交付\n2\n0\n0\n0\n0\n0\n今天 12:33\n已发表\n我把 Codex 接到飞书后，最大的变化不是“手机能聊天”\n1\n0\n0\n0\n0\n0\n今天 12:25\n已发表\n真实浏览器爬取方案重新评定\n1\n0\n0\n0\n0\n0\n今天 10:19\n已发表\n【测试勿发】四个 HTML Skill 横向对比\n2\n0\n0\n0\n0\n0\n今天 03:50\n已发表\n比特、MoreLogin、AdsPower 三款指纹浏览器实测对比\n11\n0\n1\n0\n0\n0\n昨天 11:39\n已发表\n我把 Codex 接到飞书后，最大的变化不是“手机能聊天”\n10\n0\n0\n0\n0\n0\n昨天 11:35\n已发表\n四个 HTML Skill 横向对比：谁负责审美，谁负责文章，谁负责交付\n10\n0\n0\n0\n0\n0\n昨天 11:25\n已发表\n真实浏览器爬取方案重新评定\n3\n0\n0\n0\n0\n0\n05月07日\n已发表\n1块钱用上 Opus 4.6/4.7？Windsurf 低价体验路线\n133\n0\n3\n0\n0\n0",
      "cls": "",
      "href": "",
      "box": {
        "x": 298.1094970703125,
        "y": 158.58470153808594,
        "w": 1316.0433349609375,
        "h": 1423.6776123046875
      }
    },
    {
      "i": 160,
      "text": "今天 14:01\n已发表\n我本地跑了一遍 HTML-in-Canvas：能跑，但还远不是生产级\n1\n0\n0\n0\n0\n0\n  \n还可以修改3次\n \n今天 12:35\n已发表\n四个 HTML Skill 横向对比：谁负责审美，谁负责文章，谁负责交付\n2\n0\n0\n0\n0\n0\n今天 12:33\n已发表\n我把 Codex 接到飞书后，最大的变化不是“手机能聊天”\n1\n0\n0\n0\n0\n0\n今天 12:25\n已发表\n真实浏览器爬取方案重新评定\n1\n0\n0\n0\n0\n0\n今天 10:19\n已发表\n【测试勿发】四个 HTML Skill 横向对比\n2\n0\n0\n0\n0\n0\n今天 03:50\n已发表\n比特、MoreLogin、AdsPower 三款指纹浏览器实测对比\n11\n0\n1\n0\n0\n0\n昨天 11:39\n已发表\n我把 Codex 接到飞书后，最大的变化不是“手机能聊天”\n10\n0\n0\n0\n0\n0\n昨天 11:35\n已发表\n四个 HTML Skill 横向对比：谁负责审美，谁负责文章，谁负责交付\n10\n0\n0\n0\n0\n0\n昨天 11:25\n已发表\n真实浏览器爬取方案重新评定\n3\n0\n0\n0\n0\n0\n05月07日\n已发表\n1块钱用上 Opus 4.6/4.7？Windsurf 低价体验路线\n133\n0\n3\n0\n0\n0",
      "cls": "",
      "href": "",
      "box": {
        "x": 298.1094970703125,
        "y": 158.58470153808594,
        "w": 1316.0433349609375,
        "h": 1423.6776123046875
      }
    },
    {
      "i": 161,
      "text": "今天 14:01\n已发表\n我本地跑了一遍 HTML-in-Canvas：能跑，但还远不是生产级\n1\n0\n0\n0\n0\n0\n  \n还可以修改3次",
      "cls": "weui-desktop-block",
      "href": "",
      "box": {
        "x": 298.1094970703125,
        "y": 158.58470153808594,
        "w": 1316.0433349609375,
        "h": 127.97520446777344
      }
    },
    {
      "i": 162,
      "text": "今天 14:01\n已发表\n我本地跑了一遍 HTML-in-Canvas：能跑，但还远不是生产级\n1\n0\n0\n0\n0\n0\n  \n还可以修改3次",
      "cls": "weui-desktop-block__main",
      "href": "",
      "box": {
        "x": 298.1094970703125,
        "y": 158.58470153808594,
        "w": 1316.0433349609375,
        "h": 127.97520446777344
      }
    },
    {
      "i": 163,
      "text": "今天 14:01\n已发表\n我本地跑了一遍 HTML-in-Canvas：能跑，但还远不是生产级\n1\n0\n0\n0\n0\n0\n  \n还可以修改3次",
      "cls": "weui-desktop-block__content",
      "href": "",
      "box": {
        "x": 306.1053771972656,
        "y": 166.58058166503906,
        "w": 1300.0516357421875,
        "h": 111.98346710205078
      }
    },
    {
      "i": 164,
      "text": "今天 14:01\n已发表\n我本地跑了一遍 HTML-in-Canvas：能跑，但还远不是生产级\n1\n0\n0\n0\n0\n0\n  \n还可以修改3次",
      "cls": "weui-desktop-mass__content",
      "href": "",
      "box": {
        "x": 306.1053771972656,
        "y": 166.58058166503906,
        "w": 1300.0516357421875,
        "h": 111.98346710205078
      }
    },
    {
      "i": 165,
      "text": "今天 14:01\n已发表\n我本地跑了一遍 HTML-in-Canvas：能跑，但还远不是生产级\n1\n0\n0\n0\n0\n0\n  \n还可以修改3次",
      "cls": "publish_hover_content",
      "href": "",
      "box": {
        "x": 306.1053771972656,
        "y": 166.58058166503906,
        "w": 1300.0516357421875,
        "h": 111.98346710205078
      }
    },
    {
      "i": 174,
      "text": "我本地跑了一遍 HTML-in-Canvas：能跑，但还远不是生产级\n1\n0\n0\n0\n0\n0\n  \n还可以修改3次",
      "cls": "weui-desktop-mass-media weui-desktop-mass-appmsg",
      "href": "",
      "box": {
        "x": 546.084716796875,
        "y": 182.5723114013672,
        "w": 1060.072265625,
        "h": 80
      }
    },
    {
      "i": 202,
      "text": "还可以修改3次",
      "cls": "weui-desktop-mass-appmsg__ft",
      "href": "",
      "box": {
        "x": 1385.78515625,
        "y": 205.57850646972656,
        "w": 220.3719024658203,
        "h": 51.98347091674805
      }
    },
    {
      "i": 203,
      "text": "还可以修改3次",
      "cls": "weui-desktop-mass-media__opr",
      "href": "",
      "box": {
        "x": 1385.78515625,
        "y": 205.57850646972656,
        "w": 220.3719024658203,
        "h": 51.98347091674805
      }
    },
    {
      "i": 208,
      "text": "还可以修改3次",
      "cls": "weui-desktop-mass-media__opr__meta",
      "href": "",
      "box": {
        "x": 1482.04541015625,
        "y": 205.57850646972656,
        "w": 35.99173355102539,
        "h": 35.99173355102539
      }
    },
    {
      "i": 209,
      "text": "还可以修改3次",
      "cls": "weui-desktop-tooltip__wrp weui-desktop-link",
      "href": "",
      "box": {
        "x": 1482.04541015625,
        "y": 205.57850646972656,
        "w": 35.99173355102539,
        "h": 35.99173355102539
      }
    },
    {
      "i": 211,
      "text": "还可以修改3次",
      "cls": "weui-desktop-tooltip weui-desktop-tooltip__down-center weui-desktop-tooltip__fade-enter weui-desktop-tooltip__fade-enter-active",
      "href": "",
      "box": {
        "x": 1452.5257568359375,
        "y": 171.57025146484375,
        "w": 95.03099060058594,
        "h": 24.008264541625977
      }
    },
    {
      "i": 212,
      "text": "置顶 仅自己可见 删除 关闭推荐 复制链接 \n                  添加合集\n                  声明创作来源",
      "cls": "weui-desktop-mass-media__opr__meta",
      "href": "",
      "box": {
        "x": 1538.1715087890625,
        "y": 205.57850646972656,
        "w": 35.99173355102539,
        "h": 35.99173355102539
      }
    },
    {
      "i": 213,
      "text": "置顶 仅自己可见 删除 关闭推荐 复制链接 \n                  添加合集\n                  声明创作来源",
      "cls": "more_icon",
      "href": "",
      "box": {
        "x": 1538.1715087890625,
        "y": 205.57850646972656,
        "w": 35.99173355102539,
        "h": 35.99173355102539
      }
    },
    {
      "i": 214,
      "text": "置顶 仅自己可见 删除 关闭推荐 复制链接 \n                  添加合集\n                  声明创作来源",
      "cls": "weui-desktop-popover__wrp",
      "href": "",
      "box": {
        "x": 1538.1715087890625,
        "y": 205.57850646972656,
        "w": 35.99173355102539,
        "h": 35.99173355102539
      }
    },
    {
      "i": 259,
      "text": "发表后第二日上午才可查看数据   恢复后用户将正常访问此页面，确定恢复？该入口为恢复故障数据的临时入口，将在9月11日零点关闭。 确定 取消  还可以修改3次                                                                                      置顶 仅自己可见 删除 关闭推荐 复制链接 \n                  添加合集\n                  声明创作来源",
      "cls": "weui-desktop-mass-appmsg__ft",
      "href": "",
      "box": {
        "x": 1385.78515625,
        "y": 349.5454406738281,
        "w": 220.3719024658203,
        "h": 51.98347091674805
      }
    },
    {
      "i": 260,
      "text": "发表后第二日上午才可查看数据   恢复后用户将正常访问此页面，确定恢复？该入口为恢复故障数据的临时入口，将在9月11日零点关闭。 确定 取消  还可以修改3次                                                                                      置顶 仅自己可见 删除 关闭推荐 复制链接 \n                  添加合集\n                  声明创作来源",
      "cls": "weui-desktop-mass-media__opr",
      "href": "",
      "box": {
        "x": 1385.78515625,
        "y": 349.5454406738281,
        "w": 220.3719024658203,
        "h": 51.98347091674805
      }
    },
    {
      "i": 265,
      "text": "还可以修改3次",
      "cls": "weui-desktop-mass-media__opr__meta",
      "href": "",
      "box": {
        "x": 1482.04541015625,
        "y": 349.5454406738281,
        "w": 35.99173355102539,
        "h": 35.99173355102539
      }
    },
    {
      "i": 266,
      "text": "还可以修改3次",
      "cls": "weui-desktop-tooltip__wrp weui-desktop-link",
      "href": "",
      "box": {
        "x": 1482.04541015625,
        "y": 349.5454406738281,
        "w": 35.99173355102539,
        "h": 35.99173355102539
      }
    },
    {
      "i": 268,
      "text": "置顶 仅自己可见 删除 关闭推荐 复制链接 \n                  添加合集\n                  声明创作来源",
      "cls": "weui-desktop-mass-media__opr__meta",
      "href": "",
      "box": {
        "x": 1538.1715087890625,
        "y": 349.5454406738281,
        "w": 35.99173355102539,
        "h": 35.99173355102539
      }
    },
    {
      "i": 269,
      "text": "置顶 仅自己可见 删除 关闭推荐 复制链接 \n                  添加合集\n                  声明创作来源",
      "cls": "more_icon",
      "href": "",
      "box": {
        "x": 1538.1715087890625,
        "y": 349.5454406738281,
        "w": 35.99173355102539,
        "h": 35.99173355102539
      }
    },
    {
      "i": 270,
      "text": "置顶 仅自己可见 删除 关闭推荐 复制链接 \n                  添加合集\n                  声明创作来源",
      "cls": "weui-desktop-popover__wrp",
      "href": "",
      "box": {
        "x": 1538.1715087890625,
        "y": 349.5454406738281,
        "w": 35.99173355102539,
        "h": 35.99173355102539
      }
    },
    {
      "i": 315,
      "text": "发表后第二日上午才可查看数据   恢复后用户将正常访问此页面，确定恢复？该入口为恢复故障数据的临时入口，将在9月11日零点关闭。 确定 取消  还可以修改3次                                                                                      置顶 仅自己可见 删除 关闭推荐 复制链接 \n                  添加合集\n                  声明创作来源",
      "cls": "weui-desktop-mass-appmsg__ft",
      "href": "",
      "box": {
        "x": 1385.78515625,
        "y": 493.51239013671875,
        "w": 220.3719024658203,
        "h": 51.98347091674805
      }
    },
    {
      "i": 316,
      "text": "发表后第二日上午才可查看数据   恢复后用户将正常访问此页面，确定恢复？该入口为恢复故障数据的临时入口，将在9月11日零点关闭。 确定 取消  还可以修改3次                                                                                      置顶 仅自己可见 删除 关闭推荐 复制链接 \n                  添加合集\n                  声明创作来源",
      "cls": "weui-desktop-mass-media__opr",
      "href": "",
      "box": {
        "x": 1385.78515625,
        "y": 493.51239013671875,
        "w": 220.3719024658203,
        "h": 51.98347091674805
      }
    },
    {
      "i": 321,
      "text": "还可以修改3次",
      "cls": "weui-desktop-mass-media__opr__meta",
      "href": "",
      "box": {
        "x": 1482.04541015625,
        "y": 493.51239013671875,
        "w": 35.99173355102539,
        "h": 35.99173355102539
      }
    },
    {
      "i": 322,
      "text": "还可以修改3次",
      "cls": "weui-desktop-tooltip__wrp weui-desktop-link",
      "href": "",
      "box": {
        "x": 1482.04541015625,
        "y": 493.51239013671875,
        "w": 35.99173355102539,
        "h": 35.99173355102539
      }
    },
    {
      "i": 324,
      "text": "置顶 仅自己可见 删除 关闭推荐 复制链接 \n                  添加合集\n                  声明创作来源",
      "cls": "weui-desktop-mass-media__opr__meta",
      "href": "",
      "box": {
        "x": 1538.1715087890625,
        "y": 493.51239013671875,
        "w": 35.99173355102539,
        "h": 35.99173355102539
      }
    },
    {
      "i": 325,
      "text": "置顶 仅自己可见 删除 关闭推荐 复制链接 \n                  添加合集\n                  声明创作来源",
      "cls": "more_icon",
      "href": "",
      "box": {
        "x": 1538.1715087890625,
        "y": 493.51239013671875,
        "w": 35.99173355102539,
        "h": 35.99173355102539
      }
    },
    {
      "i": 326,
      "text": "置顶 仅自己可见 删除 关闭推荐 复制链接 \n                  添加合集\n                  声明创作来源",
      "cls": "weui-desktop-popover__wrp",
      "href": "",
      "box": {
        "x": 1538.1715087890625,
        "y": 493.51239013671875,
        "w": 35.99173355102539,
        "h": 35.99173355102539
      }
    },
    {
      "i": 371,
      "text": "发表后第二日上午才可查看数据   恢复后用户将正常访问此页面，确定恢复？该入口为恢复故障数据的临时入口，将在9月11日零点关闭。 确定 取消  还可以修改3次                                                                                      置顶 仅自己可见 删除 关闭推荐 复制链接 \n                  添加合集\n                  声明创作来源",
      "cls": "weui-desktop-mass-appmsg__ft",
      "href": "",
      "box": {
        "x": 1385.78515625,
        "y": 637.4793090820312,
        "w": 220.3719024658203,
        "h": 51.98347091674805
      }
    },
    {
      "i": 372,
      "text": "发表后第二日上午才可查看数据   恢复后用户将正常访问此页面，确定恢复？该入口为恢复故障数据的临时入口，将在9月11日零点关闭。 确定 取消  还可以修改3次                                                                                      置顶 仅自己可见 删除 关闭推荐 复制链接 \n                  添加合集\n                  声明创作来源",
      "cls": "weui-desktop-mass-media__opr",
      "href": "",
      "box": {
        "x": 1385.78515625,
        "y": 637.4793090820312,
        "w": 220.3719024658203,
        "h": 51.98347091674805
      }
    },
    {
      "i": 377,
      "text": "还可以修改3次",
      "cls": "weui-desktop-mass-media__opr__meta",
      "href": "",
      "box": {
        "x": 1482.04541015625,
        "y": 637.4793090820312,
        "w": 35.99173355102539,
        "h": 35.99173355102539
      }
    },
    {
      "i": 378,
      "text": "还可以修改3次",
      "cls": "weui-desktop-tooltip__wrp weui-desktop-link",
      "href": "",
      "box": {
        "x": 1482.04541015625,
        "y": 637.4793090820312,
        "w": 35.99173355102539,
        "h": 35.99173355102539
      }
    },
    {
      "i": 380,
      "text": "置顶 仅自己可见 删除 关闭推荐 复制链接 \n                  添加合集\n                  声明创作来源",
      "cls": "weui-desktop-mass-media__opr__meta",
      "href": "",
      "box": {
        "x": 1538.1715087890625,
        "y": 637.4793090820312,
        "w": 35.99173355102539,
        "h": 35.99173355102539
      }
    },
    {
      "i": 381,
      "text": "置顶 仅自己可见 删除 关闭推荐 复制链接 \n                  添加合集\n                  声明创作来源",
      "cls": "more_icon",
      "href": "",
      "box": {
        "x": 1538.1715087890625,
        "y": 637.4793090820312,
        "w": 35.99173355102539,
        "h": 35.99173355102539
      }
    },
    {
      "i": 382,
      "text": "置顶 仅自己可见 删除 关闭推荐 复制链接 \n                  添加合集\n                  声明创作来源",
      "cls": "weui-desktop-popover__wrp",
      "href": "",
      "box": {
        "x": 1538.1715087890625,
        "y": 637.4793090820312,
        "w": 35.99173355102539,
        "h": 35.99173355102539
      }
    },
    {
      "i": 427,
      "text": "发表后第二日上午才可查看数据   恢复后用户将正常访问此页面，确定恢复？该入口为恢复故障数据的临时入口，将在9月11日零点关闭。 确定 取消  还可以修改3次                                                                                      置顶 仅自己可见 删除 关闭推荐 复制链接 \n                  添加合集\n                  声明创作来源",
      "cls": "weui-desktop-mass-appmsg__ft",
      "href": "",
      "box": {
        "x": 1385.78515625,
        "y": 781.4462890625,
        "w": 220.3719024658203,
        "h": 51.98347091674805
      }
    },
    {
      "i": 428,
      "text": "发表后第二日上午才可查看数据   恢复后用户将正常访问此页面，确定恢复？该入口为恢复故障数据的临时入口，将在9月11日零点关闭。 确定 取消  还可以修改3次                                                                                      置顶 仅自己可见 删除 关闭推荐 复制链接 \n                  添加合集\n                  声明创作来源",
      "cls": "weui-desktop-mass-media__opr",
      "href": "",
      "box": {
        "x": 1385.78515625,
        "y": 781.4462890625,
        "w": 220.3719024658203,
        "h": 51.98347091674805
      }
    },
    {
      "i": 433,
      "text": "还可以修改3次",
      "cls": "weui-desktop-mass-media__opr__meta",
      "href": "",
      "box": {
        "x": 1482.04541015625,
        "y": 781.4462890625,
        "w": 35.99173355102539,
        "h": 35.99173355102539
      }
    },
    {
      "i": 434,
      "text": "还可以修改3次",
      "cls": "weui-desktop-tooltip__wrp weui-desktop-link",
      "href": "",
      "box": {
        "x": 1482.04541015625,
        "y": 781.4462890625,
        "w": 35.99173355102539,
        "h": 35.99173355102539
      }
    },
    {
      "i": 436,
      "text": "置顶 仅自己可见 删除 关闭推荐 复制链接 \n                  添加合集\n                  声明创作来源",
      "cls": "weui-desktop-mass-media__opr__meta",
      "href": "",
      "box": {
        "x": 1538.1715087890625,
        "y": 781.4462890625,
        "w": 35.99173355102539,
        "h": 35.99173355102539
      }
    },
    {
      "i": 437,
      "text": "置顶 仅自己可见 删除 关闭推荐 复制链接 \n                  添加合集\n                  声明创作来源",
      "cls": "more_icon",
      "href": "",
      "box": {
        "x": 1538.1715087890625,
        "y": 781.4462890625,
        "w": 35.99173355102539,
        "h": 35.99173355102539
      }
    },
    {
      "i": 438,
      "text": "置顶 仅自己可见 删除 关闭推荐 复制链接 \n                  添加合集\n                  声明创作来源",
      "cls": "weui-desktop-popover__wrp",
      "href": "",
      "box": {
        "x": 1538.1715087890625,
        "y": 781.4462890625,
        "w": 35.99173355102539,
        "h": 35.99173355102539
      }
    },
    {
      "i": 483,
      "text": "发表后第二日上午才可查看数据   恢复后用户将正常访问此页面，确定恢复？该入口为恢复故障数据的临时入口，将在9月11日零点关闭。 确定 取消  还可以修改3次                                                                                      置顶 仅自己可见 删除 关闭推荐 复制链接 \n                  添加合集\n                  声明创作来源",
      "cls": "weui-desktop-mass-appmsg__ft",
      "href": "",
      "box": {
        "x": 1385.78515625,
        "y": 925.4132080078125,
        "w": 220.3719024658203,
        "h": 51.98347091674805
      }
    },
    {
      "i": 484,
      "text": "发表后第二日上午才可查看数据   恢复后用户将正常访问此页面，确定恢复？该入口为恢复故障数据的临时入口，将在9月11日零点关闭。 确定 取消  还可以修改3次                                                                                      置顶 仅自己可见 删除 关闭推荐 复制链接 \n                  添加合集\n                  声明创作来源",
      "cls": "weui-desktop-mass-media__opr",
      "href": "",
      "box": {
        "x": 1385.78515625,
        "y": 925.4132080078125,
        "w": 220.3719024658203,
        "h": 51.98347091674805
      }
    },
    {
      "i": 489,
      "text": "还可以修改3次",
      "cls": "weui-desktop-mass-media__opr__meta",
      "href": "",
      "box": {
        "x": 1482.04541015625,
        "y": 925.4132080078125,
        "w": 35.99173355102539,
        "h": 35.99173355102539
      }
    },
    {
      "i": 490,
      "text": "还可以修改3次",
      "cls": "weui-desktop-tooltip__wrp weui-desktop-link",
      "href": "",
      "box": {
        "x": 1482.04541015625,
        "y": 925.4132080078125,
        "w": 35.99173355102539,
        "h": 35.99173355102539
      }
    },
    {
      "i": 492,
      "text": "置顶 仅自己可见 删除 关闭推荐 复制链接 \n                  添加合集\n                  声明创作来源",
      "cls": "weui-desktop-mass-media__opr__meta",
      "href": "",
      "box": {
        "x": 1538.1715087890625,
        "y": 925.4132080078125,
        "w": 35.99173355102539,
        "h": 35.99173355102539
      }
    },
    {
      "i": 493,
      "text": "置顶 仅自己可见 删除 关闭推荐 复制链接 \n                  添加合集\n                  声明创作来源",
      "cls": "more_icon",
      "href": "",
      "box": {
        "x": 1538.1715087890625,
        "y": 925.4132080078125,
        "w": 35.99173355102539,
        "h": 35.99173355102539
      }
    },
    {
      "i": 494,
      "text": "置顶 仅自己可见 删除 关闭推荐 复制链接 \n                  添加合集\n                  声明创作来源",
      "cls": "weui-desktop-popover__wrp",
      "href": "",
      "box": {
        "x": 1538.1715087890625,
        "y": 925.4132080078125,
        "w": 35.99173355102539,
        "h": 35.99173355102539
      }
    },
    {
      "i": 539,
      "text": "发表数据   恢复后用户将正常访问此页面，确定恢复？该入口为恢复故障数据的临时入口，将在9月11日零点关闭。 确定 取消  还可以修改3次                                                                                      置顶 仅自己可见 删除 关闭推荐 复制链接 \n                  添加合集\n                  声明创作来源",
      "cls": "weui-desktop-mass-appmsg__ft",
      "href": "",
      "box": {
        "x": 1385.78515625,
        "y": 1069.380126953125,
        "w": 220.3719024658203,
        "h": 51.98347091674805
      }
    },
    {
      "i": 540,
      "text": "发表数据   恢复后用户将正常访问此页面，确定恢复？该入口为恢复故障数据的临时入口，将在9月11日零点关闭。 确定 取消  还可以修改3次                                                                                      置顶 仅自己可见 删除 关闭推荐 复制链接 \n                  添加合集\n                  声明创作来源",
      "cls": "weui-desktop-mass-media__opr",
      "href": "",
      "box": {
        "x": 1385.78515625,
        "y": 1069.380126953125,
        "w": 220.3719024658203,
        "h": 51.98347091674805
      }
    },
    {
      "i": 545,
      "text": "还可以修改3次",
      "cls": "weui-desktop-mass-media__opr__meta",
      "href": "",
      "box": {
        "x": 1482.04541015625,
        "y": 1069.380126953125,
        "w": 35.99173355102539,
        "h": 35.99173355102539
      }
    },
    {
      "i": 546,
      "text": "还可以修改3次",
      "cls": "weui-desktop-tooltip__wrp weui-desktop-link",
      "href": "",
      "box": {
        "x": 1482.04541015625,
        "y": 1069.380126953125,
        "w": 35.99173355102539,
        "h": 35.99173355102539
      }
    },
    {
      "i": 548,
      "text": "置顶 仅自己可见 删除 关闭推荐 复制链接 \n                  添加合集\n                  声明创作来源",
      "cls": "weui-desktop-mass-media__opr__meta",
      "href": "",
      "box": {
        "x": 1538.1715087890625,
        "y": 1069.380126953125,
        "w": 35.99173355102539,
        "h": 35.99173355102539
      }
    },
    {
      "i": 549,
      "text": "置顶 仅自己可见 删除 关闭推荐 复制链接 \n                  添加合集\n                  声明创作来源",
      "cls": "more_icon",
      "href": "",
      "box": {
        "x": 1538.1715087890625,
        "y": 1069.380126953125,
        "w": 35.99173355102539,
        "h": 35.99173355102539
      }
    },
    {
      "i": 550,
      "text": "置顶 仅自己可见 删除 关闭推荐 复制链接 \n                  添加合集\n                  声明创作来源",
      "cls": "weui-desktop-popover__wrp",
      "href": "",
      "box": {
        "x": 1538.1715087890625,
        "y": 1069.380126953125,
        "w": 35.99173355102539,
        "h": 35.99173355102539
      }
    },
    {
      "i": 595,
      "text": "发表数据   恢复后用户将正常访问此页面，确定恢复？该入口为恢复故障数据的临时入口，将在9月11日零点关闭。 确定 取消  还可以修改3次                                                                                      置顶 仅自己可见 删除 关闭推荐 复制链接 \n                  添加合集\n                  声明创作来源",
      "cls": "weui-desktop-mass-appmsg__ft",
      "href": "",
      "box": {
        "x": 1385.78515625,
        "y": 1213.3470458984375,
        "w": 220.3719024658203,
        "h": 51.98347091674805
      }
    },
    {
      "i": 596,
      "text": "发表数据   恢复后用户将正常访问此页面，确定恢复？该入口为恢复故障数据的临时入口，将在9月11日零点关闭。 确定 取消  还可以修改3次                                                                                      置顶 仅自己可见 删除 关闭推荐 复制链接 \n                  添加合集\n                  声明创作来源",
      "cls": "weui-desktop-mass-media__opr",
      "href": "",
      "box": {
        "x": 1385.78515625,
        "y": 1213.3470458984375,
        "w": 220.3719024658203,
        "h": 51.98347091674805
      }
    },
    {
      "i": 601,
      "text": "还可以修改3次",
      "cls": "weui-desktop-mass-media__opr__meta",
      "href": "",
      "box": {
        "x": 1482.04541015625,
        "y": 1213.3470458984375,
        "w": 35.99173355102539,
        "h": 35.99173355102539
      }
    },
    {
      "i": 602,
      "text": "还可以修改3次",
      "cls": "weui-desktop-tooltip__wrp weui-desktop-link",
      "href": "",
      "box": {
        "x": 1482.04541015625,
        "y": 1213.3470458984375,
        "w": 35.99173355102539,
        "h": 35.99173355102539
      }
    },
    {
      "i": 604,
      "text": "置顶 仅自己可见 删除 关闭推荐 复制链接 \n                  添加合集\n                  声明创作来源",
      "cls": "weui-desktop-mass-media__opr__meta",
      "href": "",
      "box": {
        "x": 1538.1715087890625,
        "y": 1213.3470458984375,
        "w": 35.99173355102539,
        "h": 35.99173355102539
      }
    },
    {
      "i": 605,
      "text": "置顶 仅自己可见 删除 关闭推荐 复制链接 \n                  添加合集\n                  声明创作来源",
      "cls": "more_icon",
      "href": "",
      "box": {
        "x": 1538.1715087890625,
        "y": 1213.3470458984375,
        "w": 35.99173355102539,
        "h": 35.99173355102539
      }
    },
    {
      "i": 606,
      "text": "置顶 仅自己可见 删除 关闭推荐 复制链接 \n                  添加合集\n                  声明创作来源",
      "cls": "weui-desktop-popover__wrp",
      "href": "",
      "box": {
        "x": 1538.1715087890625,
        "y": 1213.3470458984375,
        "w": 35.99173355102539,
        "h": 35.99173355102539
      }
    },
    {
      "i": 651,
      "text": "发表数据   恢复后用户将正常访问此页面，确定恢复？该入口为恢复故障数据的临时入口，将在9月11日零点关闭。 确定 取消  还可以修改3次                                                                                      置顶 仅自己可见 删除 关闭推荐 复制链接 \n                  添加合集\n                  声明创作来源",
      "cls": "weui-desktop-mass-appmsg__ft",
      "href": "",
      "box": {
        "x": 1385.78515625,
        "y": 1357.31396484375,
        "w": 220.3719024658203,
        "h": 51.98347091674805
      }
    },
    {
      "i": 652,
      "text": "发表数据   恢复后用户将正常访问此页面，确定恢复？该入口为恢复故障数据的临时入口，将在9月11日零点关闭。 确定 取消  还可以修改3次                                                                                      置顶 仅自己可见 删除 关闭推荐 复制链接 \n                  添加合集\n                  声明创作来源",
      "cls": "weui-desktop-mass-media__opr",
      "href": "",
      "box": {
        "x": 1385.78515625,
        "y": 1357.31396484375,
        "w": 220.3719024658203,
        "h": 51.98347091674805
      }
    },
    {
      "i": 657,
      "text": "还可以修改3次",
      "cls": "weui-desktop-mass-media__opr__meta",
      "href": "",
      "box": {
        "x": 1482.04541015625,
        "y": 1357.31396484375,
        "w": 35.99173355102539,
        "h": 35.99173355102539
      }
    },
    {
      "i": 658,
      "text": "还可以修改3次",
      "cls": "weui-desktop-tooltip__wrp weui-desktop-link",
      "href": "",
      "box": {
        "x": 1482.04541015625,
        "y": 1357.31396484375,
        "w": 35.99173355102539,
        "h": 35.99173355102539
      }
    },
    {
      "i": 660,
      "text": "置顶 仅自己可见 删除 关闭推荐 复制链接 \n                  添加合集\n                  声明创作来源",
      "cls": "weui-desktop-mass-media__opr__meta",
      "href": "",
      "box": {
        "x": 1538.1715087890625,
        "y": 1357.31396484375,
        "w": 35.99173355102539,
        "h": 35.99173355102539
      }
    },
    {
      "i": 661,
      "text": "置顶 仅自己可见 删除 关闭推荐 复制链接 \n                  添加合集\n                  声明创作来源",
      "cls": "more_icon",
      "href": "",
      "box": {
        "x": 1538.1715087890625,
        "y": 1357.31396484375,
        "w": 35.99173355102539,
        "h": 35.99173355102539
      }
    },
    {
      "i": 662,
      "text": "置顶 仅自己可见 删除 关闭推荐 复制链接 \n                  添加合集\n                  声明创作来源",
      "cls": "weui-desktop-popover__wrp",
      "href": "",
      "box": {
        "x": 1538.1715087890625,
        "y": 1357.31396484375,
        "w": 35.99173355102539,
        "h": 35.99173355102539
      }
    },
    {
      "i": 707,
      "text": "发表数据   恢复后用户将正常访问此页面，确定恢复？该入口为恢复故障数据的临时入口，将在9月11日零点关闭。 确定 取消  还可以修改3次                                                                                      置顶 仅自己可见 删除 关闭推荐 复制链接 \n                  添加合集\n                  声明创作来源",
      "cls": "weui-desktop-mass-appmsg__ft",
      "href": "",
      "box": {
        "x": 1385.78515625,
        "y": 1501.281005859375,
        "w": 220.3719024658203,
        "h": 51.98347091674805
      }
    },
    {
      "i": 708,
      "text": "发表数据   恢复后用户将正常访问此页面，确定恢复？该入口为恢复故障数据的临时入口，将在9月11日零点关闭。 确定 取消  还可以修改3次                                                                                      置顶 仅自己可见 删除 关闭推荐 复制链接 \n                  添加合集\n                  声明创作来源",
      "cls": "weui-desktop-mass-media__opr",
      "href": "",
      "box": {
        "x": 1385.78515625,
        "y": 1501.281005859375,
        "w": 220.3719024658203,
        "h": 51.98347091674805
      }
    },
    {
      "i": 713,
      "text": "还可以修改3次",
      "cls": "weui-desktop-mass-media__opr__meta",
      "href": "",
      "box": {
        "x": 1482.04541015625,
        "y": 1501.281005859375,
        "w": 35.99173355102539,
        "h": 35.99173355102539
      }
    },
    {
      "i": 714,
      "text": "还可以修改3次",
      "cls": "weui-desktop-tooltip__wrp weui-desktop-link",
      "href": "",
      "box": {
        "x": 1482.04541015625,
        "y": 1501.281005859375,
        "w": 35.99173355102539,
        "h": 35.99173355102539
      }
    },
    {
      "i": 716,
      "text": "置顶 仅自己可见 删除 关闭推荐 复制链接 \n                  添加合集\n                  声明创作来源",
      "cls": "weui-desktop-mass-media__opr__meta",
      "href": "",
      "box": {
        "x": 1538.1715087890625,
        "y": 1501.281005859375,
        "w": 35.99173355102539,
        "h": 35.99173355102539
      }
    },
    {
      "i": 717,
      "text": "置顶 仅自己可见 删除 关闭推荐 复制链接 \n                  添加合集\n                  声明创作来源",
      "cls": "more_icon",
      "href": "",
      "box": {
        "x": 1538.1715087890625,
        "y": 1501.281005859375,
        "w": 35.99173355102539,
        "h": 35.99173355102539
      }
    },
    {
      "i": 718,
      "text": "置顶 仅自己可见 删除 关闭推荐 复制链接 \n                  添加合集\n                  声明创作来源",
      "cls": "weui-desktop-popover__wrp",
      "href": "",
      "box": {
        "x": 1538.1715087890625,
        "y": 1501.281005859375,
        "w": 35.99173355102539,
        "h": 35.99173355102539
      }
    }
  ],
  "textEnd": "首页\n内容管理\n草稿箱\n素材库\n发表记录\n原创\n合集\n互动管理\n留言\n划线\n私信\n提到\n投票\n视频弹幕\n自动回复\n自定义菜单\n用户管理\n号内搜索\n数据分析\n收入变现\n赞赏\n付费\n带货\n流量主\n微信小店\n广告与服务\n广告主\n小程序管理\n模板消息\n微信搜一搜\n微信支付\n服务市场\n设置与开发\n新的功能\n通知中心\n45\nsinnple coffee\n发表记录\n全部 12\n已通知 6\n未通知 6\n置顶 0\n今天 14:01\n已发表\n我本地跑了一遍 HTML-in-Canvas：能跑，但还远不是生产级\n1\n0\n0\n0\n0\n0\n  \n还可以修改3次\n \n今天 12:35\n已发表\n四个 HTML Skill 横向对比：谁负责审美，谁负责文章，谁负责交付\n2\n0\n0\n0\n0\n0\n今天 12:33\n已发表\n我把 Codex 接到飞书后，最大的变化不是“手机能聊天”\n1\n0\n0\n0\n0\n0\n今天 12:25\n已发表\n真实浏览器爬取方案重新评定\n1\n0\n0\n0\n0\n0\n今天 10:19\n已发表\n【测试勿发】四个 HTML Skill 横向对比\n2\n0\n0\n0\n0\n0\n今天 03:50\n已发表\n比特、MoreLogin、AdsPower 三款指纹浏览器实测对比\n11\n0\n1\n0\n0\n0\n昨天 11:39\n已发表\n我把 Codex 接到飞书后，最大的变化不是“手机能聊天”\n10\n0\n0\n0\n0\n0\n昨天 11:35\n已发表\n四个 HTML Skill 横向对比：谁负责审美，谁负责文章，谁负责交付\n10\n0\n0\n0\n0\n0\n昨天 11:25\n已发表\n真实浏览器爬取方案重新评定\n3\n0\n0\n0\n0\n0\n05月07日\n已发表\n1块钱用上 Opus 4.6/4.7？Windsurf 低价体验路线\n133\n0\n3\n0\n0\n0\n1 2 下一页  跳转\n\n关于腾讯 服务协议 规则中心 腾讯客服 侵权投诉 反馈官号weixingongzhong 上传日志\n\nCopyright © 2012-2026 Tencent. All Rights Reserved.\n\nCDP Bridge"
}